extension/__init__.py
extension/__version__.py
extension/emojis.json
extension/resources/Accessories-calculator.svg
extension/resources/Accessories-character-map.svg
extension/resources/Accessories-text-editor.svg
extension/resources/Address-book-new.svg
extension/resources/Application-certificate.svg
extension/resources/Application-x-executable.svg
extension/resources/Applications-accessories.svg
extension/resources/Applications-development.svg
extension/resources/Applications-games.svg
extension/resources/Applications-graphics.svg
extension/resources/Applications-internet.svg
extension/resources/Applications-multimedia.svg
extension/resources/Applications-office.svg
extension/resources/Applications-other.svg
extension/resources/Applications-system.svg
extension/resources/Appointment-new.svg
extension/resources/Audio-card.svg
extension/resources/Audio-input-microphone.svg
extension/resources/Audio-volume-high.svg
extension/resources/Audio-volume-low.svg
extension/resources/Audio-volume-medium.svg
extension/resources/Audio-volume-muted.svg
extension/resources/Audio-x-generic.svg
extension/resources/Battery-caution.svg
extension/resources/Battery.svg
extension/resources/Bookmark-new.svg
extension/resources/Camera-photo.svg
extension/resources/Camera-video.svg
extension/resources/Computer.svg
extension/resources/Contact-new.svg
extension/resources/Dialog-error.svg
extension/resources/Dialog-information.svg
extension/resources/Dialog-warning.svg
extension/resources/Document-new.svg
extension/resources/Document-open.svg
extension/resources/Document-print-preview.svg
extension/resources/Document-print.svg
extension/resources/Document-properties.svg
extension/resources/Document-save-as.svg
extension/resources/Document-save.svg
extension/resources/Drive-cdrom.svg
extension/resources/Drive-harddisk.svg
extension/resources/Drive-removable-media.svg
extension/resources/Edit-clear.svg
extension/resources/Edit-copy.svg
extension/resources/Edit-cut.svg
extension-1.0.0.dist-info/LICENSE
extension-1.0.0.dist-info/METADATA
extension-1.0.0.dist-info/WHEEL
extension-1.0.0.dist-info/top_level.txt
extension-1.0.0.dist-info/RECORD
