Metadata-Version: 2.1
Name: extension
Version: 1.0.0
Summary: Utilities for python.
Home-page: UNKNOWN
Author: Yannick Kirschen
Author-email: github.yannickkirschen@protonmail.com
License: UNKNOWN
Platform: UNKNOWN
Classifier: Programming Language :: Python :: 3
Classifier: License :: OSI Approved :: GNU General Public License v3 (GPLv3)
Classifier: Operating System :: OS Independent
Classifier: Operating System :: OS Independent
Classifier: Intended Audience :: Developers
Classifier: Natural Language :: English
